guardrails_api/__init__.py
guardrails_api/app.py
guardrails_api/config.py
guardrails_api/default.env
guardrails_api/open-api-spec.json
guardrails_api/open_api_spec.py
guardrails_api/py.typed
guardrails_api/start-dev.sh
guardrails_api/start.sh
guardrails_api/blueprints/__init__.py
guardrails_api/blueprints/guards.py
guardrails_api/blueprints/root.py
guardrails_api/classes/__init__.py
guardrails_api/classes/health_check.py
guardrails_api/classes/http_error.py
guardrails_api/cli/__init__.py
guardrails_api/cli/cli.py
guardrails_api/cli/start.py
guardrails_api/clients/__init__.py
guardrails_api/clients/cache_client.py
guardrails_api/clients/guard_client.py
guardrails_api/clients/memory_guard_client.py
guardrails_api/clients/pg_guard_client.py
guardrails_api/clients/postgres_client.py
guardrails_api/models/__init__.py
guardrails_api/models/base.py
guardrails_api/models/guard_item.py
guardrails_api/models/guard_item_audit.py
guardrails_api/otel/__init__.py
guardrails_api/otel/constants.py
guardrails_api/otel/logs.py
guardrails_api/otel/metrics.py
guardrails_api/otel/traces.py
guardrails_api/utils/__init__.py
guardrails_api/utils/configuration.py
guardrails_api/utils/escape_curlys.py
guardrails_api/utils/file.py
guardrails_api/utils/gather_request_metrics.py
guardrails_api/utils/get_llm_callable.py
guardrails_api/utils/handle_error.py
guardrails_api/utils/has_internet_connection.py
guardrails_api/utils/logger.py
guardrails_api/utils/openai.py
guardrails_api/utils/payload_validator.py
guardrails_api/utils/pluck.py
guardrails_api/utils/remove_nones.py
guardrails_api/utils/trace_server_start_if_enabled.py
guardrails_api/utils/try_json_loads.py
tests/__init__.py
tests/blueprints/__init__.py
tests/blueprints/test_guards.py
tests/blueprints/test_root.py
tests/clients/__init__.py
tests/clients/test_mem_guard_client.py
tests/clients/test_pg_guard_client.py
guardrails_api-0.0.5.dist-info/LICENSE
guardrails_api-0.0.5.dist-info/METADATA
guardrails_api-0.0.5.dist-info/WHEEL
guardrails_api-0.0.5.dist-info/entry_points.txt
guardrails_api-0.0.5.dist-info/top_level.txt
guardrails_api-0.0.5.dist-info/RECORD
