Metadata-Version: 2.1
Name: guardrails-api
Version: 0.0.5
Summary: Guardrails API
Author-email: Guardrails AI <contact@guardrailsai.com>
License: ## THE FOLLOWING LICENSE HAS BEEN ADOPTED FROM THE ELSSTIC LICENSE ##
Keywords: Guardrails,Guardrails AI,Guardrails API,Guardrails API
Requires-Python: >=3.8, <4
License-File: LICENSE
Requires-Dist: guardrails-ai <0.6.0,>=0.5.6
Requires-Dist: flask <4,>=3.0.3
Requires-Dist: Flask-SQLAlchemy <4,>=3.1.1
Requires-Dist: Flask-Caching <3,>=2.3.0
Requires-Dist: Werkzeug <4,>=3.0.3
Requires-Dist: jsonschema <5,>=4.22.0
Requires-Dist: referencing <1,>=0.35.1
Requires-Dist: Flask-Cors <6,>=4.0.1
Requires-Dist: boto3 <2,>=1.34.115
Requires-Dist: psycopg2-binary <3,>=2.9.9
Requires-Dist: litellm <2,>=1.39.3
Requires-Dist: typer <1,>=0.9.4
Requires-Dist: opentelemetry-api <2,>=1.0.0
Requires-Dist: opentelemetry-sdk <2,>=1.0.0
Requires-Dist: opentelemetry-exporter-otlp-proto-grpc <2,>=1.0.0
Requires-Dist: opentelemetry-exporter-otlp-proto-http <2,>=1.0.0
Requires-Dist: opentelemetry-instrumentation-flask <1,>=0.12b0
Requires-Dist: requests >=2.32.3
Provides-Extra: dev
Requires-Dist: ruff ; extra == 'dev'
Requires-Dist: pytest ; extra == 'dev'
Requires-Dist: coverage ; extra == 'dev'
Requires-Dist: pytest-mock ; extra == 'dev'
Requires-Dist: gunicorn <23,>=22.0.0 ; extra == 'dev'
